apollo/__init__.py
apollo/apollo_client.py
apollo/python_2x.py
apollo/python_3x.py
apollo/util.py
demo/__init__.py
demo/demo.py
demo/demo_listener.py
demo/demo_secret.py
apollo_client_python-1.0.1.dist-info/METADATA
apollo_client_python-1.0.1.dist-info/WHEEL
apollo_client_python-1.0.1.dist-info/top_level.txt
apollo_client_python-1.0.1.dist-info/RECORD
